fuzzly/__init__.py
fuzzly/constants.py
fuzzly/internal.py
fuzzly/api/__init__.py
fuzzly/api/post.py
fuzzly/api/tag.py
fuzzly/client/__init__.py
fuzzly/models/__init__.py
fuzzly/models/_database.py
fuzzly/models/_shared.py
fuzzly/models/auth.py
fuzzly/models/config.py
fuzzly/models/internal.py
fuzzly/models/post.py
fuzzly/models/tag.py
fuzzly/models/user.py
fuzzly-0.0.4.dist-info/LICENSE
fuzzly-0.0.4.dist-info/METADATA
fuzzly-0.0.4.dist-info/WHEEL
fuzzly-0.0.4.dist-info/top_level.txt
fuzzly-0.0.4.dist-info/RECORD
