Metadata-Version: 2.1
Name: fuzzly
Version: 0.0.4
Summary: Fuzz.ly client library for Python3
Home-page: https://github.com/kheina-com/fuzzly
Author: kheina
License: Mozilla Public License 2.0
Requires-Python: >=3.9
License-File: LICENSE
Requires-Dist: kh-common[logging] (>=0.7.1)
